quick_log/__init__.py
quick_log/watch_logging.py
quick_log-0.1.dist-info/METADATA
quick_log-0.1.dist-info/WHEEL
quick_log-0.1.dist-info/top_level.txt
quick_log-0.1.dist-info/RECORD
