Metadata-Version: 2.1
Name: quick-log
Version: 0.1
Summary: 用于快速创建日志句柄，避免重复的设置相关参数
Home-page: https://github.com/luxp4588/quick_log.git
Author: python-xp
Author-email: luxp4588@126.com
License: MIT
Keywords: logger logging
Platform: any
Classifier: Development Status :: 5 - Production/Stable
Classifier: Environment :: Web Environment
Classifier: Intended Audience :: Developers
Classifier: License :: OSI Approved :: MIT License
Classifier: Programming Language :: Python :: 3.5
Classifier: Programming Language :: Python :: 3.6
Classifier: Programming Language :: Python :: 3.7
Classifier: Programming Language :: Python :: 3.8
Classifier: Programming Language :: Python :: 3.9
Classifier: Topic :: Internet :: WWW/HTTP :: Dynamic Content
Classifier: Topic :: Software Development :: Libraries :: Python Modules
